spectrum_fundamentals/__init__.py
spectrum_fundamentals/__main__.py
spectrum_fundamentals/annotation/__init__.py
spectrum_fundamentals/annotation/annotation.py
spectrum_fundamentals/charge.py
spectrum_fundamentals/constants.py
spectrum_fundamentals/fragments.py
spectrum_fundamentals/metrics/__init__.py
spectrum_fundamentals/metrics/fragments_ratio.py
spectrum_fundamentals/metrics/metric.py
spectrum_fundamentals/metrics/percolator.py
spectrum_fundamentals/metrics/similarity.py
spectrum_fundamentals/mod_string.py
spectrum_fundamentals/py.typed
spectrum_fundamentals-0.9.0.dist-info/LICENSE
spectrum_fundamentals-0.9.0.dist-info/METADATA
spectrum_fundamentals-0.9.0.dist-info/WHEEL
spectrum_fundamentals-0.9.0.dist-info/entry_points.txt
spectrum_fundamentals-0.9.0.dist-info/RECORD
