Metadata-Version: 2.3
Name: spectrum_fundamentals
Version: 0.9.0
Summary: Fundamental functions, annotation pipeline and constants for oktoberfest
License: MIT
Author: Wilhelmlab at Technical University of Munich
Requires-Python: >=3.10,<3.14.0
Classifier: License :: OSI Approved :: MIT License
Classifier: Programming Language :: Python :: 3
Classifier: Programming Language :: Python :: 3.10
Classifier: Programming Language :: Python :: 3.11
Classifier: Programming Language :: Python :: 3.12
Classifier: Programming Language :: Python :: 3.13
Requires-Dist: PyYAML (>=5.4.1)
Requires-Dist: click (>=8.0.0)
Requires-Dist: joblib (>=1.0.1,<2.0.0)
Requires-Dist: moepy (>=1.1.4,<2.0.0)
Requires-Dist: numpy (>=1.24.1)
Requires-Dist: pandas (>=1.3,<3.0)
Requires-Dist: rich (>=10.3.0)
Requires-Dist: scikit-learn (>=1.5,<2.0)
Project-URL: Documentation, https://spectrum-fundamentals.readthedocs.io
Project-URL: Homepage, https://github.com/wilhelm-lab/spectrum_fundamentals
Project-URL: Repository, https://github.com/wilhelm-lab/spectrum_fundamentals
